.coveragerc
CHANGELOG.md
LICENSE
MANIFEST.in
README.md
pyproject.toml
pytest.ini
setup.cfg
setup.py
docs/.gitignore
docs/Makefile
docs/clear-automodapis.sh
docs/conf.py
docs/index.rst
docs/installation.rst
docs/make.bat
docs/_static/.gitignore
docs/api/wwt_api_client.APIRequest.rst
docs/api/wwt_api_client.APIResponseError.rst
docs/api/wwt_api_client.Client.rst
docs/api/wwt_api_client.InvalidRequestError.rst
docs/api/wwt_api_client.LoginRequest.rst
docs/api/wwt_api_client.ShowImageRequest.rst
docs/api/wwt_api_client.TileImageRequest.rst
docs/api/wwt_api_client.communities.CommunitiesAPIRequest.rst
docs/api/wwt_api_client.communities.CommunitiesClient.rst
docs/api/wwt_api_client.communities.CreateCommunityRequest.rst
docs/api/wwt_api_client.communities.DeleteCommunityRequest.rst
docs/api/wwt_api_client.communities.GetCommunityInfoRequest.rst
docs/api/wwt_api_client.communities.GetLatestCommunityRequest.rst
docs/api/wwt_api_client.communities.GetMyProfileRequest.rst
docs/api/wwt_api_client.communities.GetProfileEntitiesRequest.rst
docs/api/wwt_api_client.communities.IsUserRegisteredRequest.rst
docs/api/wwt_api_client.communities.interactive_communities_login.rst
docs/api/wwt_api_client.communities.rst
docs/api/wwt_api_client.constellations.ClientConfig.rst
docs/api/wwt_api_client.constellations.CxClient.rst
docs/api/wwt_api_client.constellations.data.HandleImageStats.rst
docs/api/wwt_api_client.constellations.data.HandleInfo.rst
docs/api/wwt_api_client.constellations.data.HandlePermissions.rst
docs/api/wwt_api_client.constellations.data.HandleSceneStats.rst
docs/api/wwt_api_client.constellations.data.HandleStats.rst
docs/api/wwt_api_client.constellations.data.HandleUpdate.rst
docs/api/wwt_api_client.constellations.data.ImageApiPermissions.rst
docs/api/wwt_api_client.constellations.data.ImageContentPermissions.rst
docs/api/wwt_api_client.constellations.data.ImageDisplayInfo.rst
docs/api/wwt_api_client.constellations.data.ImageInfo.rst
wwt_api_client.egg-info/PKG-INFO
wwt_api_client.egg-info/SOURCES.txt
wwt_api_client.egg-info/dependency_links.txt
wwt_api_client.egg-info/requires.txt
wwt_api_client.egg-info/top_level.txt
